linse/__init__.py
linse/annotate.py
linse/models.py
linse/profile.py
linse/sampa.py
linse/segment.py
linse/subsequence.py
linse/transform.py
linse/typedsequence.py
linse/util.py
linse/data/clts.zip
linse/data/normalize.tsv
linse/data/sampa.csv
linse/models/art/INFO
linse/models/art/converter
linse/models/art_el/INFO
linse/models/art_el/converter
linse/models/asjp/INFO
linse/models/asjp/converter
linse/models/asjp_el/INFO
linse/models/asjp_el/converter
linse/models/burmish/converter
linse/models/color/INFO
linse/models/color/converter
linse/models/color_el/INFO
linse/models/color_el/converter
linse/models/cv/INFO
linse/models/cv/converter
linse/models/diss/INFO
linse/models/diss/converter
linse/models/dolgo/INFO
linse/models/dolgo/converter
linse/models/dolgo_el/INFO
linse/models/dolgo_el/converter
linse/models/dvt/diacritics
linse/models/dvt/tones
linse/models/dvt/vowels
linse/models/dvt_el/diacritics
linse/models/dvt_el/tones
linse/models/dvt_el/vowels
linse/models/gamb_el/converter
linse/models/internal_asjp/INFO
linse/models/internal_asjp/converter
linse/models/jaeger/INFO
linse/models/jaeger/converter
linse/models/jaeger_el/INFO
linse/models/jaeger_el/converter
linse/models/sca/INFO
linse/models/sca/converter
linse/models/sca_el/INFO
linse/models/sca_el/converter
linse-0.1.0.dist-info/LICENSE
linse-0.1.0.dist-info/METADATA
linse-0.1.0.dist-info/WHEEL
linse-0.1.0.dist-info/top_level.txt
linse-0.1.0.dist-info/RECORD
